parcoursup/README.md
parcoursup/__init__.py
parcoursup/ordreappel/AlgoOrdreAppel.py
parcoursup/ordreappel/GroupeClassement.py
parcoursup/ordreappel/OrdreAppel.py
parcoursup/ordreappel/VoeuClasse.py
parcoursup/ordreappel/__init__.py
parcoursup/ordreappel/exemples.py
parcoursup/propositions/AlgoPropositions.py
parcoursup/propositions/Candidat.py
parcoursup/propositions/Etablissement.py
parcoursup/propositions/GroupeAffectation.py
parcoursup/propositions/GroupeAffectationUID.py
parcoursup/propositions/GroupeInternat.py
parcoursup/propositions/GroupeInternatUID.py
parcoursup/propositions/VerificationsResultats.py
parcoursup/propositions/VoeuEnAttente.py
parcoursup/propositions/VoeuUID.py
parcoursup/propositions/__init__.py
parcoursup/propositions/exemples.py
parcoursup-0.2.1.dist-info/DESCRIPTION.rst
parcoursup-0.2.1.dist-info/METADATA
parcoursup-0.2.1.dist-info/RECORD
parcoursup-0.2.1.dist-info/WHEEL
parcoursup-0.2.1.dist-info/metadata.json
parcoursup-0.2.1.dist-info/top_level.txt
