Metadata-Version: 2.0
Name: parcoursup
Version: 0.2.1
Summary: ParcourSup.py : un clone en Python 3 de ParcoursSup, écrit à but didactique
Home-page: https://github.com/Naereen/ParcourSup.py/
Author: Lilian Besson
Author-email: naereen@crans.org
License: MIT
Download-URL: https://github.com/Naereen/ParcourSup.py/releases/
Keywords: parcoursup,python3,clone-libre,open-source,france,exemple,lycee,education-nationale,visualisations,algorithmes
Platform: GNU/Linux
Classifier: Development Status :: 4 - Beta
Classifier: Environment :: Console
Classifier: Intended Audience :: Science/Research
Classifier: License :: OSI Approved :: MIT License
Classifier: Natural Language :: English
Classifier: Operating System :: Unix
Classifier: Programming Language :: Python :: 3.4
Classifier: Programming Language :: Python :: 3.5
Classifier: Programming Language :: Python :: 3.6
Requires-Dist: numpy
Requires-Dist: tqdm (>=4.0)
Requires-Dist: jupyter
Requires-Dist: ipython
Requires-Dist: watermark
Requires-Dist: ipythonblocks
Requires-Dist: sphinx
Requires-Dist: sphinx-rtd-theme
Requires-Dist: recommonmark
